tfExperiment/__init__.py
tfExperiment/cacheManager.py
tfExperiment/dispossableSession.py
tfExperiment/errors.py
tfExperiment/experiment.py
tfExperiment/initNew.py
tfExperiment/withinPath.py
tfExperiment-1.1.7.dist-info/METADATA
tfExperiment-1.1.7.dist-info/WHEEL
tfExperiment-1.1.7.dist-info/top_level.txt
tfExperiment-1.1.7.dist-info/RECORD
