Metadata-Version: 2.1
Name: tfExperiment
Version: 1.1.7
Summary: A simple library to manage Tensorflow experiments though git and reduce boilerplate. Compatible with tf 1.x
Home-page: https://github.com/Pensarfeo/tfExperiment
Author: Pedro A. Favuzzi
Author-email: pa.favuzzi@gmail.com
License: UNKNOWN
Platform: UNKNOWN
Classifier: Programming Language :: Python :: 3
Classifier: License :: OSI Approved :: MIT License
Classifier: Operating System :: OS Independent
Requires-Dist: python-box
Requires-Dist: dataSaver
Requires-Dist: stepTimer
Requires-Dist: pygit2
